{
  "generator-jhipster": {
    "applicationType": "monolith",
    "authenticationType": "oauth2",
    "baseName": "CupHubTmp",
    "blueprints": [],
    "buildTool": "maven",
    "cacheProvider": "redis",
    "clientFramework": "angular",
    "clientPackageManager": "npm",
    "creationTimestamp": 1727773079433,
    "databaseType": "sql",
    "devDatabaseType": "h2Disk",
    "devServerPort": 4200,
    "enableHibernateCache": true,
    "enableSwaggerCodegen": "true",
    "enableTranslation": true,
    "entities": [],
    "gitCompany": "",
    "jhiPrefix": "jhi",
    "jhipsterVersion": "8.7.1",
    "languages": ["en", "ua"],
    "messageBroker": false,
    "nativeLanguage": "en",
    "packageFolder": "xyz/vshmaliukh/app",
    "packageName": "xyz.vshmaliukh.app",
    "prodDatabaseType": "postgresql",
    "searchEngine": "elasticsearch",
    "serverPort": 8080,
    "serviceDiscoveryType": false,
    "skipUserManagement": true,
    "testFrameworks": ["cucumber"],
    "useSass": true,
    "websocket": false,
    "withAdminUi": true
  },
  "git-company": "shmaliukh",
  "git-provider": "GitHub",
  "repository-name": "cup-hub-tmp"
}
